{
    "Deafness": 126.81,
    "Miki_Hoshii": 122.97,
    "Sniparook": 120.58,
    "koroshiya": 119.27,
    "comfv": 116.38,
    "kar72": 112.18,
    "Diukes": 109.49,
    "Thaleko": 108.31,
    "Milar": 102.72,
    "Baikinman": 102.65,
    "Alkios": 102.17,
    "mrwolf2": 98.37,
    "beautiful": 97.87,
    "Nicole": 96.2,
    "Comete": 95.78,
    "Hejsan": 94.97,
    "kaededayo": 93.74,
    "Mami": 93.72,
    "Dry": 90.39,
    "Orfey": 90.37,
    "Pile": 87.11,
    "Chata": 86.94,
    "Neumann": 86.44,
    "HaruUrara": 85.52,
    "Flato": 81.35,
    "yasashiikumo": 79.05,
    "cafezinho": 78.73,
    "fiftypercentweeb": 77.53,
    "Provenance": 76.47,
    "md22": 75.74,
    "AnnaYanami": 75.73,
    "Saiki": 74.73,
    "chaabdu92": 74.7,
    "Janoxx": 73.67,
    "Yolowolf75": 73.57,
    "MoltenAshes": 71.85,
    "Kirox": 70.94,
    "xeyz": 70.55,
    "mahzrunner": 69.96,
    "Spartric": 69.59,
    "ponbot": 69.26,
    "Heleos": 66.9,
    "Poppysr": 66.42,
    "MaikaSasaki": 66.25,
    "Tugia": 65.1,
    "Tvaz": 64.65,
    "kabao": 64.15,
    "Vr0003": 61.57,
    "Unborned": 55.15,
    "Shiku": 54.7,
    "inta": 53.52,
    "OkitaNobu": 53.27,
    "Bewm": 52.82,
    "Patoche49": 51.96,
    "MapleSyyrup": 47.8,
    "FoopyPoopy": 38.32,
    "lotte_616": 36.01
}