{
	"tour_id": "watched_house_20260612_034445",
	"time": "2026-06-12 03:44:45.077098+00:00",
	"teams": {
		"redeyes (20.88) cm02 (12.54) catge (11.09) liljakatsuragi (9.47) = 53.98": "1W 0L 0D",
		"i_dont_like_loli (19.53) arpia97 (15.47) caramel36 (15.47) dking20 (2.53) = 53.00": "0W 1L 0D"
	},
	"player": {
		"redeyes": "initial elo: 20.879, new elo: 22.918, rating change: 2.039",
		"cm02": "initial elo: 12.540, new elo: 15.774, rating change: 3.233",
		"catge": "initial elo: 11.092, new elo: 13.586, rating change: 2.494",
		"liljakatsuragi": "initial elo: 9.473, new elo: 11.512, rating change: 2.039",
		"i_dont_like_loli": "initial elo: 19.527, new elo: 17.488, rating change: -2.039",
		"arpia97": "initial elo: 15.473, new elo: 13.434, rating change: -2.039",
		"caramel36": "initial elo: 15.473, new elo: 13.434, rating change: -2.039",
		"dking20": "initial elo: 2.527, new elo: 0.488, rating change: -2.039"
	}
}